estimagic/__init__.py
estimagic/batch_evaluators.py
estimagic/bootstrap.py
estimagic/bootstrap_ci.py
estimagic/bootstrap_helpers.py
estimagic/bootstrap_outcomes.py
estimagic/bootstrap_samples.py
estimagic/config.py
estimagic/estimate_ml.py
estimagic/estimate_msm.py
estimagic/estimation_summaries.py
estimagic/estimation_table.py
estimagic/lollipop_plot.py
estimagic/ml_covs.py
estimagic/msm_covs.py
estimagic/msm_sensitivity.py
estimagic/msm_weighting.py
estimagic/py.typed
estimagic/shared_covs.py
estimagic/utilities.py
estimagic/examples/__init__.py
estimagic/examples/diabetes.csv
estimagic/examples/exam_points.csv
estimagic/examples/logit.py
estimagic/examples/sensitivity_probit_example_data.csv
optimagic/__init__.py
optimagic/_version.py
optimagic/algorithms.py
optimagic/batch_evaluators.py
optimagic/config.py
optimagic/constraints.py
optimagic/decorators.py
optimagic/deprecations.py
optimagic/exceptions.py
optimagic/mark.py
optimagic/py.typed
optimagic/timing.py
optimagic/type_conversion.py
optimagic/typing.py
optimagic/utilities.py
optimagic/benchmarking/__init__.py
optimagic/benchmarking/benchmark_reports.py
optimagic/benchmarking/cartis_roberts.py
optimagic/benchmarking/get_benchmark_problems.py
optimagic/benchmarking/more_wild.py
optimagic/benchmarking/noise_distributions.py
optimagic/benchmarking/process_benchmark_results.py
optimagic/benchmarking/run_benchmark.py
optimagic/differentiation/__init__.py
optimagic/differentiation/derivatives.py
optimagic/differentiation/finite_differences.py
optimagic/differentiation/generate_steps.py
optimagic/differentiation/numdiff_options.py
optimagic/differentiation/richardson_extrapolation.py
optimagic/examples/__init__.py
optimagic/examples/criterion_functions.py
optimagic/examples/numdiff_functions.py
optimagic/logging/__init__.py
optimagic/logging/base.py
optimagic/logging/logger.py
optimagic/logging/read_log.py
optimagic/logging/sqlalchemy.py
optimagic/logging/types.py
optimagic/optimization/__init__.py
optimagic-0.5.2.dist-info/METADATA
optimagic-0.5.2.dist-info/WHEEL
optimagic-0.5.2.dist-info/licenses/LICENSE
optimagic-0.5.2.dist-info/RECORD
