Metadata-Version: 2.4
Name: optimagic
Version: 0.5.2
Summary: Tools to solve difficult numerical optimization problems.
Project-URL: Repository, https://github.com/optimagic-dev/optimagic
Project-URL: Github, https://github.com/optimagic-dev/optimagic
Project-URL: Tracker, https://github.com/optimagic-dev/optimagic/issues
Author-email: Janos Gabler <janos.gabler@gmail.com>
Maintainer-email: Janos Gabler <janos.gabler@gmail.com>, Tim Mensinger <mensingertim@gmail.com>
License: MIT
License-File: LICENSE
Keywords: derivative free optimization,estimation,extremum estimation,finite differences,global optimization,inference,maximum likelihood,method of simulated moments,nonlinear optimization,numerical differentiation,optimization,parallel optimization,statistics
Classifier: Development Status :: 5 - Production/Stable
Classifier: Intended Audience :: Science/Research
Classifier: License :: OSI Approved :: MIT License
Classifier: Operating System :: MacOS :: MacOS X
Classifier: Operating System :: Microsoft :: Windows
Classifier: Operating System :: POSIX
Classifier: Programming Language :: Python :: 3.10
Classifier: Programming Language :: Python :: 3.11
Classifier: Programming Language :: Python :: 3.12
Classifier: Programming Language :: Python :: 3.13
Classifier: Topic :: Scientific/Engineering
Requires-Python: >=3.10
Requires-Dist: annotated-types
Requires-Dist: cloudpickle
Requires-Dist: joblib
Requires-Dist: numpy
Requires-Dist: pandas
Requires-Dist: plotly
Requires-Dist: pybaum>=0.1.2
Requires-Dist: scipy>=1.2.1
Requires-Dist: sqlalchemy>=1.3
Requires-Dist: typing-extensions
